odoo/addons/partner_private_information_autocomplete/README.rst
odoo/addons/partner_private_information_autocomplete/__init__.py
odoo/addons/partner_private_information_autocomplete/__manifest__.py
odoo/addons/partner_private_information_autocomplete/i18n/es.po
odoo/addons/partner_private_information_autocomplete/models/__init__.py
odoo/addons/partner_private_information_autocomplete/models/res_partner.py
odoo/addons/partner_private_information_autocomplete/readme/CONTRIBUTORS.md
odoo/addons/partner_private_information_autocomplete/readme/DESCRIPTION.md
odoo/addons/partner_private_information_autocomplete/readme/USAGE.md
odoo/addons/partner_private_information_autocomplete/static/description/icon.png
odoo/addons/partner_private_information_autocomplete/static/description/index.html
odoo/addons/partner_private_information_autocomplete/views/res_partner_view.xml
odoo_addon_partner_private_information_autocomplete-17.0.1.0.0.1.dist-info/METADATA
odoo_addon_partner_private_information_autocomplete-17.0.1.0.0.1.dist-info/WHEEL
odoo_addon_partner_private_information_autocomplete-17.0.1.0.0.1.dist-info/top_level.txt
odoo_addon_partner_private_information_autocomplete-17.0.1.0.0.1.dist-info/RECORD
