Metadata-Version: 2.1
Name: odoo-addon-partner_private_information_autocomplete
Version: 17.0.1.0.0.1
Requires-Python: >=3.10
Requires-Dist: odoo-addon-base_location>=17.0dev,<17.1dev
Requires-Dist: odoo-addon-partner_private_information>=17.0dev,<17.1dev
Requires-Dist: odoo>=17.0a,<17.1dev
Summary: Autocomplete private information tab in partners.
Home-page: https://github.com/sygel-technology/sy-partner-contact
License: AGPL-3
Author: Sygel, Odoo Community Association (OCA)
Author-email: support@odoo-community.org
Classifier: Programming Language :: Python
Classifier: Framework :: Odoo
Classifier: Framework :: Odoo :: 17.0
Classifier: License :: OSI Approved :: GNU Affero General Public License v3
